MANIFEST.in
README.md
setup.cfg
setup.py
src/colab_superarchives/__init__.py
src/colab_superarchives/admin.py
src/colab_superarchives/apps.py
src/colab_superarchives/context_processors.py
src/colab_superarchives/filters.py
src/colab_superarchives/managers.py
src/colab_superarchives/models.py
src/colab_superarchives/search_indexes.py
src/colab_superarchives/signals.py
src/colab_superarchives/urls.py
src/colab_superarchives/views.py
src/colab_superarchives.egg-info/PKG-INFO
src/colab_superarchives.egg-info/SOURCES.txt
src/colab_superarchives.egg-info/dependency_links.txt
src/colab_superarchives.egg-info/not-zip-safe
src/colab_superarchives.egg-info/requires.txt
src/colab_superarchives.egg-info/top_level.txt
src/colab_superarchives/fixtures/mailinglistdata.json
src/colab_superarchives/fixtures/test_data_superachives.json
src/colab_superarchives/locale/en/LC_MESSAGES/django.mo
src/colab_superarchives/locale/en/LC_MESSAGES/django.po
src/colab_superarchives/locale/es/LC_MESSAGES/django.mo
src/colab_superarchives/locale/es/LC_MESSAGES/django.po
src/colab_superarchives/locale/pt_BR/LC_MESSAGES/django.mo
src/colab_superarchives/locale/pt_BR/LC_MESSAGES/django.po
src/colab_superarchives/management/__init__.py
src/colab_superarchives/management/commands/__init__.py
src/colab_superarchives/management/commands/import_emails.py
src/colab_superarchives/management/commands/message.py
src/colab_superarchives/management/commands/update_blocks.py
src/colab_superarchives/management/commands/update_keywords.py
src/colab_superarchives/migrations/0001_initial.py
src/colab_superarchives/migrations/0002_thread_user.py
src/colab_superarchives/migrations/__init__.py
src/colab_superarchives/templates/mailinglist-summary.html
src/colab_superarchives/templates/message-preview.html
src/colab_superarchives/templates/message-thread.html
src/colab_superarchives/templates/dashboard/thread_search_preview.html
src/colab_superarchives/templates/search/thread_search_preview.html
src/colab_superarchives/templates/search/indexes/colab_superarchives/thread_collaborators.txt
src/colab_superarchives/templates/search/indexes/colab_superarchives/thread_description.txt
src/colab_superarchives/templates/search/indexes/colab_superarchives/thread_text.txt
