Metadata-Version: 1.1
Name: colab-superarchives
Version: 0.1.0
Summary: Super Archives (Mailman) plugin for Colab
Home-page: https://github.com/colab/colab-superarchives-plugin
Author: Charles Oliveira
Author-email: 18oliveira.charles@gmail.com
License: GPLv3
Platform: UNKNOWN
Classifier: Framework :: Django
Classifier: Intended Audience :: Developers
Classifier: Intended Audience :: System Administrators
Classifier: Operating System :: OS Independent
Classifier: Topic :: Software Development
